django_jsform/.DS_Store
django_jsform/__init__.py
django_jsform/js_response.py
django_jsform/py.typed
django_jsform/__pycache__/__init__.cpython-311.pyc
django_jsform/__pycache__/__init__.cpython-312.pyc
django_jsform/__pycache__/__init__.cpython-36.pyc
django_jsform/__pycache__/__init__.cpython-37.pyc
django_jsform/__pycache__/__init__.cpython-39.pyc
django_jsform/__pycache__/js_response.cpython-311.pyc
django_jsform/__pycache__/js_response.cpython-312.pyc
django_jsform/__pycache__/js_response.cpython-36.pyc
django_jsform/__pycache__/js_response.cpython-37.pyc
django_jsform/__pycache__/js_response.cpython-39.pyc
django_jsform/django_jsform.egg-info/PKG-INFO
django_jsform/django_jsform.egg-info/SOURCES.txt
django_jsform/django_jsform.egg-info/dependency_links.txt
django_jsform/django_jsform.egg-info/requires.txt
django_jsform/django_jsform.egg-info/top_level.txt
django_jsform/js_helpers/clear_form_errors.js
django_jsform/js_helpers/focus_form_errors.js
django_jsform/js_helpers/set_form_errors.js
django_jsform/static/django_jsform/django_jsform.css
django_jsform/static/jsform/.git
django_jsform/static/jsform/LICENSE
django_jsform/static/jsform/README.md
django_jsform/static/jsform/alert_something.js
django_jsform/static/jsform/alert_something_multiple.js
django_jsform/static/jsform/jsform.js
django_jsform/static/jsform/jsform_elementmerge.js
django_jsform/static/jsform/jsform_execresponse.js
django_jsform/static/jsform/jsform_focus_error_element.js
django_jsform/templates/.DS_Store
django_jsform/templates/django_jsform/checkbox_field.html
django_jsform/templates/django_jsform/complete_form.html
django_jsform/templates/django_jsform/form_fields.html
django_jsform/templates/django_jsform/form_test.html
django_jsform/templates/django_jsform/inline_field.html
django_jsform/templates/django_jsform/standard_field.html
django_jsform/templatetags/.DS_Store
django_jsform/templatetags/jsform.py
django_jsform/templatetags/py.typed
django_jsform/templatetags/__pycache__/jsform.cpython-311.pyc
django_jsform/templatetags/__pycache__/jsform.cpython-312.pyc
django_jsform/templatetags/__pycache__/jsform.cpython-36.pyc
django_jsform/templatetags/__pycache__/jsform.cpython-37.pyc
django_jsform-5.7.1.dist-info/LICENSE
django_jsform-5.7.1.dist-info/METADATA
django_jsform-5.7.1.dist-info/WHEEL
django_jsform-5.7.1.dist-info/top_level.txt
django_jsform-5.7.1.dist-info/RECORD
