Metadata-Version: 2.1
Name: django-jsform
Version: 5.7.1
Summary: Django integration for jsform
Home-page: https://github.com/quadrant-newmedia/django_jsform
Author: Alex Fischer
Author-email: alex@quadrant.net
License: UNKNOWN
Platform: UNKNOWN
Classifier: Programming Language :: Python :: 3
Classifier: License :: OSI Approved :: MIT License
Classifier: Operating System :: OS Independent
Requires-Python: >=3.7
License-File: LICENSE
Requires-Dist: Django <6,>=3
Requires-Dist: html-generators <3,>=2.8.0
